jsonformer/__init__.py
jsonformer/format.py
jsonformer/logits_processors.py
jsonformer/main.py
guardrails_jsonformer-0.13.1.dist-info/METADATA
guardrails_jsonformer-0.13.1.dist-info/WHEEL
guardrails_jsonformer-0.13.1.dist-info/RECORD
