Metadata-Version: 2.4
Name: guardrails-jsonformer
Version: 0.13.1
Summary: A fork of 1rgs' jsonformer maintained by Guardrails AI
Author: 1rgs
Author-email: rgsduke@gmail.com
Maintainer: Guardrails AI
Maintainer-email: contact@guardrailsai.com
Requires-Python: >=3.9,<4.0
Classifier: Programming Language :: Python :: 3
Classifier: Programming Language :: Python :: 3.9
Classifier: Programming Language :: Python :: 3.10
Classifier: Programming Language :: Python :: 3.11
Classifier: Programming Language :: Python :: 3.12
Classifier: Programming Language :: Python :: 3.13
Requires-Dist: termcolor (>=2.3.0,<3.0.0)
